gql_py/__init__.py
gql_py/gql.py
gql_py-0.6.0.dist-info/DESCRIPTION.rst
gql_py-0.6.0.dist-info/METADATA
gql_py-0.6.0.dist-info/RECORD
gql_py-0.6.0.dist-info/WHEEL
gql_py-0.6.0.dist-info/metadata.json
gql_py-0.6.0.dist-info/top_level.txt
