Metadata-Version: 2.0
Name: gql-py
Version: 0.6.0
Summary: GraphQL Client for Pythonistas
Home-page: https://github.com/phalt/gql_py
Author: Paul Hallett
Author-email: paulandrewhallett@gmail.com
License: MIT license
Keywords: graphQL
Platform: UNKNOWN
Classifier: Development Status :: 4 - Beta
Classifier: Intended Audience :: Developers
Classifier: License :: OSI Approved :: MIT License
Classifier: Natural Language :: English
Classifier: Programming Language :: Python :: 3.6
Classifier: Programming Language :: Python :: 3.7
Requires-Dist: requests (==2.19.1)
Requires-Dist: graphql-core-next (==1.0.0rc2)
